[
    {
        "title": "Australian",
        "slug": "australian",
        "results": [
            {
                "pos": "1",
                "driver": "Hamilton",
                "time": "1:31:54.067"
            },
            {
                "pos": "2",
                "driver": "Rosberg",
                "time": "+1.360"
            },
            {
                "pos": "3",
                "driver": "Vettel",
                "time": "+34.523"
            },
            {
                "pos": "4",
                "driver": "Massa",
                "time": "+38.196"
            },
            {
                "pos": "5",
                "driver": "Nasr",
                "time": "+1:35.149"
            },
            {
                "pos": "6",
                "driver": "Ricciardo"
            },
            {
                "pos": "7",
                "driver": "Hülkenberg"
            },
            {
                "pos": "8",
                "driver": "Ericsson"
            },
            {
                "pos": "9",
                "driver": "Sainz"
            },
            {
                "pos": "10",
                "driver": "Pérez"
            },
            {
                "pos": "11",
                "driver": "Button"
            },
            {
                "pos": "12",
                "driver": "Räikkönen"
            },
            {
                "pos": "13",
                "driver": "Verstappen"
            },
            {
                "pos": "14",
                "driver": "Grosjean"
            },
            {
                "pos": "15",
                "driver": "Maldonado"
            },
            {
                "pos": "16",
                "driver": "Kvyat"
            },
            {
                "pos": "17",
                "driver": "Magnussen"
            },
            {
                "pos": "18",
                "driver": "Bottas"
            }
        ]
    },
    {
        "title": "Malaysian",
        "slug": "malaysian",
        "results": [
            {
                "pos": "1",
                "driver": "Vettel",
                "time": "1:41:05.793"
            },
            {
                "pos": "2",
                "driver": "Hamilton",
                "time": "+8.569"
            },
            {
                "pos": "3",
                "driver": "Rosberg",
                "time": "+12.310"
            },
            {
                "pos": "4",
                "driver": "Räikkönen",
                "time": "+53.822"
            },
            {
                "pos": "5",
                "driver": "Bottas",
                "time": "+1:10.409"
            },
            {
                "pos": "6",
                "driver": "Massa",
                "time": "+1:13.586"
            },
            {
                "pos": "7",
                "driver": "Verstappen",
                "time": "+1:37.762"
            },
            {
                "pos": "8",
                "driver": "Sainz"
            },
            {
                "pos": "9",
                "driver": "Kvyat"
            },
            {
                "pos": "10",
                "driver": "Ricciardo"
            },
            {
                "pos": "11",
                "driver": "Grosjean"
            },
            {
                "pos": "12",
                "driver": "Nasr"
            },
            {
                "pos": "13",
                "driver": "Pérez"
            },
            {
                "pos": "14",
                "driver": "Hülkenberg"
            },
            {
                "pos": "15",
                "driver": "Merhi"
            },
            {
                "pos": "16",
                "driver": "Maldonado"
            },
            {
                "pos": "17",
                "driver": "Button"
            },
            {
                "pos": "18",
                "driver": "Alonso"
            },
            {
                "pos": "19",
                "driver": "Ericsson"
            },
            {
                "pos": "20",
                "driver": "Stevens"
            }
        ]
    },
    {
        "title": "Chinese",
        "slug": "chinese",
        "results": [
            {
                "pos": "1",
                "driver": "Hamilton",
                "time": "1:39:42.008"
            },
            {
                "pos": "2",
                "driver": "Rosberg",
                "time": "+0.714"
            },
            {
                "pos": "3",
                "driver": "Vettel",
                "time": "+2.988"
            },
            {
                "pos": "4",
                "driver": "Räikkönen",
                "time": "+3.835"
            },
            {
                "pos": "5",
                "driver": "Massa",
                "time": "+8.544"
            },
            {
                "pos": "6",
                "driver": "Bottas",
                "time": "+9.885"
            },
            {
                "pos": "7",
                "driver": "Grosjean",
                "time": "+19.008"
            },
            {
                "pos": "8",
                "driver": "Nasr",
                "time": "+22.625"
            },
            {
                "pos": "9",
                "driver": "Ricciardo",
                "time": "+32.117"
            },
            {
                "pos": "10",
                "driver": "Ericsson"
            },
            {
                "pos": "11",
                "driver": "Pérez"
            },
            {
                "pos": "12",
                "driver": "Alonso"
            },
            {
                "pos": "13",
                "driver": "Sainz"
            },
            {
                "pos": "14",
                "driver": "Button"
            },
            {
                "pos": "15",
                "driver": "Stevens"
            },
            {
                "pos": "16",
                "driver": "Merhi"
            },
            {
                "pos": "17",
                "driver": "Verstappen"
            },
            {
                "pos": "18",
                "driver": "Maldonado"
            },
            {
                "pos": "19",
                "driver": "Kvyat"
            },
            {
                "pos": "20",
                "driver": "Hülkenberg"
            }
        ]
    },
    {
        "title": "Bahrain",
        "slug": "bahrain",
        "results": [
            {
                "pos": "1",
                "driver": "Hamilton",
                "time": "1:35:05.809"
            },
            {
                "pos": "2",
                "driver": "Räikkönen",
                "time": "+3.380"
            },
            {
                "pos": "3",
                "driver": "Rosberg",
                "time": "+6.033"
            },
            {
                "pos": "4",
                "driver": "Bottas",
                "time": "+42.957"
            },
            {
                "pos": "5",
                "driver": "Vettel",
                "time": "+43.989"
            },
            {
                "pos": "6",
                "driver": "Ricciardo",
                "time": "+1:01.751"
            },
            {
                "pos": "7",
                "driver": "Grosjean",
                "time": "+1:24.763"
            },
            {
                "pos": "8",
                "driver": "Pérez"
            },
            {
                "pos": "9",
                "driver": "Kvyat"
            },
            {
                "pos": "10",
                "driver": "Massa"
            },
            {
                "pos": "11",
                "driver": "Alonso"
            },
            {
                "pos": "12",
                "driver": "Nasr"
            },
            {
                "pos": "13",
                "driver": "Hülkenberg"
            },
            {
                "pos": "14",
                "driver": "Ericsson"
            },
            {
                "pos": "15",
                "driver": "Maldonado"
            },
            {
                "pos": "16",
                "driver": "Stevens"
            },
            {
                "pos": "17",
                "driver": "Merhi"
            },
            {
                "pos": "18",
                "driver": "Verstappen"
            },
            {
                "pos": "19",
                "driver": "Sainz"
            },
            {
                "pos": "20",
                "driver": "Button"
            }
        ]
    },
    {
        "title": "Spanish",
        "slug": "spanish",
        "results": [
            {
                "pos": "1",
                "driver": "Rosberg",
                "time": "1:41:12.555"
            },
            {
                "pos": "2",
                "driver": "Hamilton",
                "time": "+17.551"
            },
            {
                "pos": "3",
                "driver": "Vettel",
                "time": "+45.342"
            },
            {
                "pos": "4",
                "driver": "Bottas",
                "time": "+59.217"
            },
            {
                "pos": "5",
                "driver": "Räikkönen",
                "time": "+1:00.002"
            },
            {
                "pos": "6",
                "driver": "Massa",
                "time": "+1:21.314"
            },
            {
                "pos": "7",
                "driver": "Ricciardo"
            },
            {
                "pos": "8",
                "driver": "Grosjean"
            },
            {
                "pos": "9",
                "driver": "Sainz"
            },
            {
                "pos": "10",
                "driver": "Kvyat"
            },
            {
                "pos": "11",
                "driver": "Verstappen"
            },
            {
                "pos": "12",
                "driver": "Nasr"
            },
            {
                "pos": "13",
                "driver": "Pérez"
            },
            {
                "pos": "14",
                "driver": "Ericsson"
            },
            {
                "pos": "15",
                "driver": "Hülkenberg"
            },
            {
                "pos": "16",
                "driver": "Button"
            },
            {
                "pos": "17",
                "driver": "Stevens"
            },
            {
                "pos": "18",
                "driver": "Merhi"
            },
            {
                "pos": "19",
                "driver": "Maldonado"
            },
            {
                "pos": "20",
                "driver": "Alonso"
            }
        ]
    },
    {
        "title": "Monaco",
        "slug": "monaco",
        "results": [
            {
                "pos": "1",
                "driver": "Rosberg",
                "time": "1:49:18.420"
            },
            {
                "pos": "2",
                "driver": "Vettel",
                "time": "+4.486"
            },
            {
                "pos": "3",
                "driver": "Hamilton",
                "time": "+6.053"
            },
            {
                "pos": "4",
                "driver": "Kvyat",
                "time": "+11.965"
            },
            {
                "pos": "5",
                "driver": "Ricciardo",
                "time": "+13.608"
            },
            {
                "pos": "6",
                "driver": "Räikkönen",
                "time": "+14.345"
            },
            {
                "pos": "7",
                "driver": "Pérez",
                "time": "+15.013"
            },
            {
                "pos": "8",
                "driver": "Button",
                "time": "+16.063"
            },
            {
                "pos": "9",
                "driver": "Nasr",
                "time": "+23.626"
            },
            {
                "pos": "10",
                "driver": "Sainz",
                "time": "+25.056"
            },
            {
                "pos": "11",
                "driver": "Hülkenberg",
                "time": "+26.232"
            },
            {
                "pos": "12",
                "driver": "Grosjean",
                "time": "+28.415"
            },
            {
                "pos": "13",
                "driver": "Ericsson",
                "time": "+31.159"
            },
            {
                "pos": "14",
                "driver": "Bottas",
                "time": "+45.789"
            },
            {
                "pos": "15",
                "driver": "Massa"
            },
            {
                "pos": "16",
                "driver": "Merhi"
            },
            {
                "pos": "17",
                "driver": "Stevens"
            },
            {
                "pos": "18",
                "driver": "Verstappen"
            },
            {
                "pos": "19",
                "driver": "Alonso"
            },
            {
                "pos": "20",
                "driver": "Maldonado"
            }
        ]
    },
    {
        "title": "Canadian",
        "slug": "canadian",
        "results": [
            {
                "pos": "1",
                "driver": "Hamilton",
                "time": "1:31:53.145"
            },
            {
                "pos": "2",
                "driver": "Rosberg",
                "time": "+2.285"
            },
            {
                "pos": "3",
                "driver": "Bottas",
                "time": "+40.666"
            },
            {
                "pos": "4",
                "driver": "Räikkönen",
                "time": "+45.625"
            },
            {
                "pos": "5",
                "driver": "Vettel",
                "time": "+49.903"
            },
            {
                "pos": "6",
                "driver": "Massa",
                "time": "+56.381"
            },
            {
                "pos": "7",
                "driver": "Maldonado",
                "time": "+1:06.664"
            },
            {
                "pos": "8",
                "driver": "Hülkenberg"
            },
            {
                "pos": "9",
                "driver": "Kvyat"
            },
            {
                "pos": "10",
                "driver": "Grosjean"
            },
            {
                "pos": "11",
                "driver": "Pérez"
            },
            {
                "pos": "12",
                "driver": "Sainz"
            },
            {
                "pos": "13",
                "driver": "Ricciardo"
            },
            {
                "pos": "14",
                "driver": "Ericsson"
            },
            {
                "pos": "15",
                "driver": "Verstappen"
            },
            {
                "pos": "16",
                "driver": "Nasr"
            },
            {
                "pos": "17",
                "driver": "Stevens"
            },
            {
                "pos": "18",
                "driver": "Merhi"
            },
            {
                "pos": "19",
                "driver": "Button"
            },
            {
                "pos": "20",
                "driver": "Alonso"
            }
        ]
    },
    {
        "title": "Austrian",
        "slug": "austrian",
        "results": [
            {
                "pos": "1",
                "driver": "Rosberg",
                "time": "1:30:16.930"
            },
            {
                "pos": "2",
                "driver": "Hamilton",
                "time": "+8.800"
            },
            {
                "pos": "3",
                "driver": "Massa",
                "time": "+17.573"
            },
            {
                "pos": "4",
                "driver": "Vettel",
                "time": "+18.181"
            },
            {
                "pos": "5",
                "driver": "Bottas",
                "time": "+53.604"
            },
            {
                "pos": "6",
                "driver": "Hülkenberg",
                "time": "+1:04.075"
            },
            {
                "pos": "7",
                "driver": "Maldonado"
            },
            {
                "pos": "8",
                "driver": "Verstappen"
            },
            {
                "pos": "9",
                "driver": "Pérez"
            },
            {
                "pos": "10",
                "driver": "Ricciardo"
            },
            {
                "pos": "11",
                "driver": "Nasr"
            },
            {
                "pos": "12",
                "driver": "Kvyat"
            },
            {
                "pos": "13",
                "driver": "Ericsson"
            },
            {
                "pos": "14",
                "driver": "Merhi"
            },
            {
                "pos": "15",
                "driver": "Grosjean"
            },
            {
                "pos": "16",
                "driver": "Sainz"
            },
            {
                "pos": "17",
                "driver": "Button"
            },
            {
                "pos": "18",
                "driver": "Stevens"
            },
            {
                "pos": "19",
                "driver": "Räikkönen"
            },
            {
                "pos": "20",
                "driver": "Alonso"
            }
        ]
    },
    {
        "title": "British",
        "slug": "british",
        "results": [
            {
                "pos": "1",
                "driver": "Hamilton",
                "time": "1:31:27.729"
            },
            {
                "pos": "2",
                "driver": "Rosberg",
                "time": "+10.956"
            },
            {
                "pos": "3",
                "driver": "Vettel",
                "time": "+25.443"
            },
            {
                "pos": "4",
                "driver": "Massa",
                "time": "+36.839"
            },
            {
                "pos": "5",
                "driver": "Bottas",
                "time": "+1:03.194"
            },
            {
                "pos": "6",
                "driver": "Kvyat",
                "time": "+1:03.955"
            },
            {
                "pos": "7",
                "driver": "Hülkenberg",
                "time": "+1:18.744"
            },
            {
                "pos": "8",
                "driver": "Räikkönen"
            },
            {
                "pos": "9",
                "driver": "Pérez"
            },
            {
                "pos": "10",
                "driver": "Alonso"
            },
            {
                "pos": "11",
                "driver": "Ericsson"
            },
            {
                "pos": "12",
                "driver": "Merhi"
            },
            {
                "pos": "13",
                "driver": "Stevens"
            },
            {
                "pos": "14",
                "driver": "Sainz"
            },
            {
                "pos": "15",
                "driver": "Ricciardo"
            },
            {
                "pos": "16",
                "driver": "Verstappen"
            },
            {
                "pos": "17",
                "driver": "Grosjean"
            },
            {
                "pos": "18",
                "driver": "Maldonado"
            },
            {
                "pos": "19",
                "driver": "Button"
            },
            {
                "pos": "20",
                "driver": "Nasr"
            }
        ]
    },
    {
        "title": "Hungarian",
        "slug": "hungarian",
        "results": [
            {
                "pos": "1",
                "driver": "Vettel",
                "time": "1:46:09.985"
            },
            {
                "pos": "2",
                "driver": "Kvyat",
                "time": "+15.748"
            },
            {
                "pos": "3",
                "driver": "Ricciardo",
                "time": "+25.084"
            },
            {
                "pos": "4",
                "driver": "Verstappen",
                "time": "+44.251"
            },
            {
                "pos": "5",
                "driver": "Alonso",
                "time": "+49.079"
            },
            {
                "pos": "6",
                "driver": "Hamilton",
                "time": "+52.025"
            },
            {
                "pos": "7",
                "driver": "Grosjean",
                "time": "+58.578"
            },
            {
                "pos": "8",
                "driver": "Rosberg",
                "time": "+58.876"
            },
            {
                "pos": "9",
                "driver": "Button",
                "time": "+1:07.028"
            },
            {
                "pos": "10",
                "driver": "Ericsson",
                "time": "+1:09.130"
            },
            {
                "pos": "11",
                "driver": "Nasr",
                "time": "+1:13.458"
            },
            {
                "pos": "12",
                "driver": "Massa",
                "time": "+1:14.278"
            },
            {
                "pos": "13",
                "driver": "Bottas",
                "time": "+1:20.228"
            },
            {
                "pos": "14",
                "driver": "Maldonado",
                "time": "+1:25.142"
            },
            {
                "pos": "15",
                "driver": "Merhi"
            },
            {
                "pos": "16",
                "driver": "Stevens"
            },
            {
                "pos": "17",
                "driver": "Sainz"
            },
            {
                "pos": "18",
                "driver": "Räikkönen"
            },
            {
                "pos": "19",
                "driver": "Pérez"
            },
            {
                "pos": "20",
                "driver": "Hülkenberg"
            }
        ]
    },
    {
        "title": "Belgian",
        "slug": "belgian",
        "results": [
            {
                "pos": "1",
                "driver": "Hamilton",
                "time": "1:23:40.387"
            },
            {
                "pos": "2",
                "driver": "Rosberg",
                "time": "+2.058"
            },
            {
                "pos": "3",
                "driver": "Grosjean",
                "time": "+37.988"
            },
            {
                "pos": "4",
                "driver": "Kvyat",
                "time": "+45.692"
            },
            {
                "pos": "5",
                "driver": "Pérez",
                "time": "+53.997"
            },
            {
                "pos": "6",
                "driver": "Massa",
                "time": "+55.283"
            },
            {
                "pos": "7",
                "driver": "Räikkönen",
                "time": "+55.703"
            },
            {
                "pos": "8",
                "driver": "Verstappen",
                "time": "+56.076"
            },
            {
                "pos": "9",
                "driver": "Bottas",
                "time": "+1:01.040"
            },
            {
                "pos": "10",
                "driver": "Ericsson",
                "time": "+1:31.234"
            },
            {
                "pos": "11",
                "driver": "Nasr",
                "time": "+1:42.311"
            },
            {
                "pos": "12",
                "driver": "Vettel"
            },
            {
                "pos": "13",
                "driver": "Alonso"
            },
            {
                "pos": "14",
                "driver": "Button"
            },
            {
                "pos": "15",
                "driver": "Merhi"
            },
            {
                "pos": "16",
                "driver": "Stevens"
            },
            {
                "pos": "17",
                "driver": "Sainz"
            },
            {
                "pos": "18",
                "driver": "Ricciardo"
            },
            {
                "pos": "19",
                "driver": "Maldonado"
            },
            {
                "pos": "20",
                "driver": "Hülkenberg"
            }
        ]
    },
    {
        "title": "Italian",
        "slug": "italian",
        "results": [
            {
                "pos": "1",
                "driver": "Hamilton",
                "time": "1:18:00.688"
            },
            {
                "pos": "2",
                "driver": "Vettel",
                "time": "+25.042"
            },
            {
                "pos": "3",
                "driver": "Massa",
                "time": "+47.635"
            },
            {
                "pos": "4",
                "driver": "Bottas",
                "time": "+47.996"
            },
            {
                "pos": "5",
                "driver": "Räikkönen",
                "time": "+1:08.860"
            },
            {
                "pos": "6",
                "driver": "Pérez",
                "time": "+1:12.783"
            },
            {
                "pos": "7",
                "driver": "Hülkenberg"
            },
            {
                "pos": "8",
                "driver": "Ricciardo"
            },
            {
                "pos": "9",
                "driver": "Ericsson"
            },
            {
                "pos": "10",
                "driver": "Kvyat"
            },
            {
                "pos": "11",
                "driver": "Sainz"
            },
            {
                "pos": "12",
                "driver": "Verstappen"
            },
            {
                "pos": "13",
                "driver": "Nasr"
            },
            {
                "pos": "14",
                "driver": "Button"
            },
            {
                "pos": "15",
                "driver": "Stevens"
            },
            {
                "pos": "16",
                "driver": "Merhi"
            },
            {
                "pos": "17",
                "driver": "Rosberg"
            },
            {
                "pos": "18",
                "driver": "Alonso"
            },
            {
                "pos": "19",
                "driver": "Grosjean"
            },
            {
                "pos": "20",
                "driver": "Maldonado"
            }
        ]
    },
    {
        "title": "Singapore",
        "slug": "singapore",
        "results": [
            {
                "pos": "1",
                "driver": "Vettel",
                "time": "2:01:22.118"
            },
            {
                "pos": "2",
                "driver": "Ricciardo",
                "time": "+1.478"
            },
            {
                "pos": "3",
                "driver": "Räikkönen",
                "time": "+17.154"
            },
            {
                "pos": "4",
                "driver": "Rosberg",
                "time": "+24.720"
            },
            {
                "pos": "5",
                "driver": "Bottas",
                "time": "+34.204"
            },
            {
                "pos": "6",
                "driver": "Kvyat",
                "time": "+35.508"
            },
            {
                "pos": "7",
                "driver": "Pérez",
                "time": "+50.836"
            },
            {
                "pos": "8",
                "driver": "Verstappen",
                "time": "+51.450"
            },
            {
                "pos": "9",
                "driver": "Sainz",
                "time": "+52.860"
            },
            {
                "pos": "10",
                "driver": "Nasr",
                "time": "+1:30.045"
            },
            {
                "pos": "11",
                "driver": "Ericsson",
                "time": "+1:37.507"
            },
            {
                "pos": "12",
                "driver": "Maldonado",
                "time": "+1:37.718"
            },
            {
                "pos": "13",
                "driver": "Grosjean"
            },
            {
                "pos": "14",
                "driver": "Rossi"
            },
            {
                "pos": "15",
                "driver": "Stevens"
            },
            {
                "pos": "16",
                "driver": "Button"
            },
            {
                "pos": "17",
                "driver": "Alonso"
            },
            {
                "pos": "18",
                "driver": "Hamilton"
            },
            {
                "pos": "19",
                "driver": "Massa"
            },
            {
                "pos": "20",
                "driver": "Hülkenberg"
            }
        ]
    },
    {
        "title": "Japanese",
        "slug": "japanese",
        "results": [
            {
                "pos": "1",
                "driver": "Hamilton",
                "time": "1:28:06.508"
            },
            {
                "pos": "2",
                "driver": "Rosberg",
                "time": "+18.964"
            },
            {
                "pos": "3",
                "driver": "Vettel",
                "time": "+20.850"
            },
            {
                "pos": "4",
                "driver": "Räikkönen",
                "time": "+33.768"
            },
            {
                "pos": "5",
                "driver": "Bottas",
                "time": "+36.746"
            },
            {
                "pos": "6",
                "driver": "Hülkenberg",
                "time": "+55.559"
            },
            {
                "pos": "7",
                "driver": "Grosjean",
                "time": "+1:12.298"
            },
            {
                "pos": "8",
                "driver": "Maldonado",
                "time": "+1:13.575"
            },
            {
                "pos": "9",
                "driver": "Verstappen",
                "time": "+1:35.315"
            },
            {
                "pos": "10",
                "driver": "Sainz"
            },
            {
                "pos": "11",
                "driver": "Alonso"
            },
            {
                "pos": "12",
                "driver": "Pérez"
            },
            {
                "pos": "13",
                "driver": "Kvyat"
            },
            {
                "pos": "14",
                "driver": "Ericsson"
            },
            {
                "pos": "15",
                "driver": "Ricciardo"
            },
            {
                "pos": "16",
                "driver": "Button"
            },
            {
                "pos": "17",
                "driver": "Massa"
            },
            {
                "pos": "18",
                "driver": "Rossi"
            },
            {
                "pos": "19",
                "driver": "Stevens"
            },
            {
                "pos": "20",
                "driver": "Nasr"
            }
        ]
    },
    {
        "title": "Russian",
        "slug": "russian",
        "results": [
            {
                "pos": "1",
                "driver": "Hamilton",
                "time": "1:37:11.024"
            },
            {
                "pos": "2",
                "driver": "Vettel",
                "time": "+5.953"
            },
            {
                "pos": "3",
                "driver": "Pérez",
                "time": "+28.918"
            },
            {
                "pos": "4",
                "driver": "Massa",
                "time": "+38.831"
            },
            {
                "pos": "5",
                "driver": "Kvyat",
                "time": "+47.566"
            },
            {
                "pos": "6",
                "driver": "Nasr",
                "time": "+56.508"
            },
            {
                "pos": "7",
                "driver": "Maldonado",
                "time": "+1:01.088"
            },
            {
                "pos": "8",
                "driver": "Räikkönen",
                "time": "+1:12.358"
            },
            {
                "pos": "9",
                "driver": "Button",
                "time": "+1:19.467"
            },
            {
                "pos": "10",
                "driver": "Verstappen",
                "time": "+1:28.424"
            },
            {
                "pos": "11",
                "driver": "Alonso",
                "time": "+1:31.210"
            },
            {
                "pos": "12",
                "driver": "Bottas"
            },
            {
                "pos": "13",
                "driver": "Merhi"
            },
            {
                "pos": "14",
                "driver": "Stevens"
            },
            {
                "pos": "15",
                "driver": "Ricciardo"
            },
            {
                "pos": "16",
                "driver": "Sainz"
            },
            {
                "pos": "17",
                "driver": "Grosjean"
            },
            {
                "pos": "18",
                "driver": "Rosberg"
            },
            {
                "pos": "19",
                "driver": "Hülkenberg"
            },
            {
                "pos": "20",
                "driver": "Ericsson"
            }
        ]
    },
    {
        "title": "United States",
        "slug": "united-states",
        "results": [
            {
                "pos": "1",
                "driver": "Hamilton",
                "time": "1:50:52.703"
            },
            {
                "pos": "2",
                "driver": "Rosberg",
                "time": "+2.850"
            },
            {
                "pos": "3",
                "driver": "Vettel",
                "time": "+3.381"
            },
            {
                "pos": "4",
                "driver": "Verstappen",
                "time": "+22.359"
            },
            {
                "pos": "5",
                "driver": "Pérez",
                "time": "+24.413"
            },
            {
                "pos": "6",
                "driver": "Button",
                "time": "+28.058"
            },
            {
                "pos": "7",
                "driver": "Sainz",
                "time": "+30.619"
            },
            {
                "pos": "8",
                "driver": "Maldonado",
                "time": "+32.273"
            },
            {
                "pos": "9",
                "driver": "Nasr",
                "time": "+40.257"
            },
            {
                "pos": "10",
                "driver": "Ricciardo",
                "time": "+53.371"
            },
            {
                "pos": "11",
                "driver": "Alonso",
                "time": "+54.816"
            },
            {
                "pos": "12",
                "driver": "Rossi",
                "time": "+1:15.277"
            },
            {
                "pos": "13",
                "driver": "Kvyat"
            },
            {
                "pos": "14",
                "driver": "Hülkenberg"
            },
            {
                "pos": "15",
                "driver": "Ericsson"
            },
            {
                "pos": "16",
                "driver": "Räikkönen"
            },
            {
                "pos": "17",
                "driver": "Massa"
            },
            {
                "pos": "18",
                "driver": "Grosjean"
            },
            {
                "pos": "19",
                "driver": "Bottas"
            },
            {
                "pos": "20",
                "driver": "Stevens"
            }
        ]
    },
    {
        "title": "Mexican",
        "slug": "mexican",
        "results": [
            {
                "pos": "1",
                "driver": "Rosberg",
                "time": "1:42:35.038"
            },
            {
                "pos": "2",
                "driver": "Hamilton",
                "time": "+1.954"
            },
            {
                "pos": "3",
                "driver": "Bottas",
                "time": "+14.592"
            },
            {
                "pos": "4",
                "driver": "Kvyat",
                "time": "+16.572"
            },
            {
                "pos": "5",
                "driver": "Ricciardo",
                "time": "+19.682"
            },
            {
                "pos": "6",
                "driver": "Massa",
                "time": "+21.493"
            },
            {
                "pos": "7",
                "driver": "Hülkenberg",
                "time": "+25.860"
            },
            {
                "pos": "8",
                "driver": "Pérez",
                "time": "+34.343"
            },
            {
                "pos": "9",
                "driver": "Verstappen",
                "time": "+35.229"
            },
            {
                "pos": "10",
                "driver": "Grosjean",
                "time": "+37.934"
            },
            {
                "pos": "11",
                "driver": "Maldonado",
                "time": "+38.538"
            },
            {
                "pos": "12",
                "driver": "Ericsson",
                "time": "+40.180"
            },
            {
                "pos": "13",
                "driver": "Sainz",
                "time": "+48.772"
            },
            {
                "pos": "14",
                "driver": "Button",
                "time": "+49.214"
            },
            {
                "pos": "15",
                "driver": "Rossi"
            },
            {
                "pos": "16",
                "driver": "Stevens"
            },
            {
                "pos": "17",
                "driver": "Nasr"
            },
            {
                "pos": "18",
                "driver": "Vettel"
            },
            {
                "pos": "19",
                "driver": "Räikkönen"
            },
            {
                "pos": "20",
                "driver": "Alonso"
            }
        ]
    },
    {
        "title": "Brazilian",
        "slug": "brazilian",
        "results": [
            {
                "pos": "1",
                "driver": "Rosberg",
                "time": "1:31:09.090"
            },
            {
                "pos": "2",
                "driver": "Hamilton",
                "time": "+7.756"
            },
            {
                "pos": "3",
                "driver": "Vettel",
                "time": "+14.244"
            },
            {
                "pos": "4",
                "driver": "Räikkönen",
                "time": "+47.543"
            },
            {
                "pos": "5",
                "driver": "Bottas"
            },
            {
                "pos": "6",
                "driver": "Hülkenberg"
            },
            {
                "pos": "7",
                "driver": "Kvyat"
            },
            {
                "pos": "8",
                "driver": "Grosjean"
            },
            {
                "pos": "9",
                "driver": "Verstappen"
            },
            {
                "pos": "10",
                "driver": "Maldonado"
            },
            {
                "pos": "11",
                "driver": "Ricciardo"
            },
            {
                "pos": "12",
                "driver": "Pérez"
            },
            {
                "pos": "13",
                "driver": "Nasr"
            },
            {
                "pos": "14",
                "driver": "Button"
            },
            {
                "pos": "15",
                "driver": "Alonso"
            },
            {
                "pos": "16",
                "driver": "Ericsson"
            },
            {
                "pos": "17",
                "driver": "Stevens"
            },
            {
                "pos": "18",
                "driver": "Rossi"
            },
            {
                "pos": "19",
                "driver": "Sainz"
            },
            {
                "pos": "20",
                "driver": "Massa"
            }
        ]
    },
    {
        "title": "Abu Dhabi",
        "slug": "abu-dhabi",
        "results": [
            {
                "pos": "1",
                "driver": "Rosberg",
                "time": "1:38:30.175"
            },
            {
                "pos": "2",
                "driver": "Hamilton",
                "time": "+8.271"
            },
            {
                "pos": "3",
                "driver": "Räikkönen",
                "time": "+19.430"
            },
            {
                "pos": "4",
                "driver": "Vettel",
                "time": "+43.735"
            },
            {
                "pos": "5",
                "driver": "Pérez",
                "time": "+1:03.952"
            },
            {
                "pos": "6",
                "driver": "Ricciardo",
                "time": "+1:05.010"
            },
            {
                "pos": "7",
                "driver": "Hülkenberg",
                "time": "+1:33.618"
            },
            {
                "pos": "8",
                "driver": "Massa",
                "time": "+1:37.751"
            },
            {
                "pos": "9",
                "driver": "Grosjean",
                "time": "+1:38.201"
            },
            {
                "pos": "10",
                "driver": "Kvyat",
                "time": "+1:42.371"
            },
            {
                "pos": "11",
                "driver": "Sainz",
                "time": "+1:43.525"
            },
            {
                "pos": "12",
                "driver": "Button"
            },
            {
                "pos": "13",
                "driver": "Bottas"
            },
            {
                "pos": "14",
                "driver": "Ericsson"
            },
            {
                "pos": "15",
                "driver": "Nasr"
            },
            {
                "pos": "16",
                "driver": "Verstappen"
            },
            {
                "pos": "17",
                "driver": "Alonso"
            },
            {
                "pos": "18",
                "driver": "Stevens"
            },
            {
                "pos": "19",
                "driver": "Merhi"
            },
            {
                "pos": "20",
                "driver": "Maldonado"
            }
        ]
    }
]
